{
  "id": "40ac911d-dc78-44bd-8fe4-d848071062d5",
  "prevId": "95ae0311-43ed-4abf-8c07-fbced6e07912",
  "version": "7",
  "dialect": "postgresql",
  "tables": {
    "public.tags": {
      "name": "tags",
      "schema": "",
      "columns": {
        "id": {
          "name": "id",
          "type": "serial",
          "primaryKey": true,
          "notNull": true
        },
        "name": {
          "name": "name",
          "type": "text",
          "primaryKey": false,
          "notNull": true
        },
        "color": {
          "name": "color",
          "type": "text",
          "primaryKey": false,
          "notNull": false,
          "default": "'#6b7280'"
        },
        "created_at": {
          "name": "created_at",
          "type": "timestamp",
          "primaryKey": false,
          "notNull": false,
          "default": "now()"
        }
      },
      "indexes": {},
      "foreignKeys": {},
      "compositePrimaryKeys": {},
      "uniqueConstraints": {
        "tags_name_unique": {
          "name": "tags_name_unique",
          "nullsNotDistinct": false,
          "columns": [
            "name"
          ]
        }
      },
      "policies": {},
      "checkConstraints": {},
      "isRLSEnabled": false
    },
    "public.video_tags": {
      "name": "video_tags",
      "schema": "",
      "columns": {
        "id": {
          "name": "id",
          "type": "serial",
          "primaryKey": true,
          "notNull": true
        },
        "video_id": {
          "name": "video_id",
          "type": "integer",
          "primaryKey": false,
          "notNull": true
        },
        "tag_id": {
          "name": "tag_id",
          "type": "integer",
          "primaryKey": false,
          "notNull": true
        }
      },
      "indexes": {},
      "foreignKeys": {
        "video_tags_video_id_videos_id_fk": {
          "name": "video_tags_video_id_videos_id_fk",
          "tableFrom": "video_tags",
          "tableTo": "videos",
          "columnsFrom": [
            "video_id"
          ],
          "columnsTo": [
            "id"
          ],
          "onDelete": "cascade",
          "onUpdate": "no action"
        },
        "video_tags_tag_id_tags_id_fk": {
          "name": "video_tags_tag_id_tags_id_fk",
          "tableFrom": "video_tags",
          "tableTo": "tags",
          "columnsFrom": [
            "tag_id"
          ],
          "columnsTo": [
            "id"
          ],
          "onDelete": "cascade",
          "onUpdate": "no action"
        }
      },
      "compositePrimaryKeys": {},
      "uniqueConstraints": {},
      "policies": {},
      "checkConstraints": {},
      "isRLSEnabled": false
    },
    "public.videos": {
      "name": "videos",
      "schema": "",
      "columns": {
        "id": {
          "name": "id",
          "type": "serial",
          "primaryKey": true,
          "notNull": true
        },
        "url": {
          "name": "url",
          "type": "text",
          "primaryKey": false,
          "notNull": true
        },
        "title": {
          "name": "title",
          "type": "text",
          "primaryKey": false,
          "notNull": false
        },
        "platform": {
          "name": "platform",
          "type": "video_platform",
          "typeSchema": "public",
          "primaryKey": false,
          "notNull": true
        },
        "thumbnail_url": {
          "name": "thumbnail_url",
          "type": "text",
          "primaryKey": false,
          "notNull": false
        },
        "is_watched": {
          "name": "is_watched",
          "type": "boolean",
          "primaryKey": false,
          "notNull": false,
          "default": false
        },
        "created_at": {
          "name": "created_at",
          "type": "timestamp",
          "primaryKey": false,
          "notNull": false,
          "default": "now()"
        },
        "updated_at": {
          "name": "updated_at",
          "type": "timestamp",
          "primaryKey": false,
          "notNull": false,
          "default": "now()"
        }
      },
      "indexes": {},
      "foreignKeys": {},
      "compositePrimaryKeys": {},
      "uniqueConstraints": {
        "videos_url_unique": {
          "name": "videos_url_unique",
          "nullsNotDistinct": false,
          "columns": [
            "url"
          ]
        }
      },
      "policies": {},
      "checkConstraints": {},
      "isRLSEnabled": false
    }
  },
  "enums": {
    "public.video_platform": {
      "name": "video_platform",
      "schema": "public",
      "values": [
        "youtube",
        "netflix",
        "nebula",
        "twitch",
        "unknown"
      ]
    }
  },
  "schemas": {},
  "sequences": {},
  "roles": {},
  "policies": {},
  "views": {},
  "_meta": {
    "columns": {},
    "schemas": {},
    "tables": {}
  }
}